testpipeci/__init__.py
testpipeci/cli.py
testpipeci-0.1.2.dist-info/METADATA
testpipeci-0.1.2.dist-info/WHEEL
testpipeci-0.1.2.dist-info/entry_points.txt
testpipeci-0.1.2.dist-info/RECORD
