Metadata-Version: 2.1
Name: testpipeci
Version: 0.1.2
Summary: 
Author: Thiago Melo
Author-email: 4thiagomelo5@gmail.com
Requires-Python: >=3.10,<4.0
Classifier: Programming Language :: Python :: 3
Classifier: Programming Language :: Python :: 3.10
Classifier: Programming Language :: Python :: 3.11
Requires-Dist: typer (>=0.9.0,<0.10.0)
